{"assets":{"AB5BA6B3CC3DD0CDD9678F6B37984E7E":{"type":"texture","index":1,"url":{"native":"assets\/743D9366-1F94-40CF-BFFE-60D111C25037.pdf"},"width":1920,"height":1080},"77B8B06DD926AFA1AE5AE9B598D05DEF":{"type":"texture","index":0,"url":{"native":"assets\/743D9366-1F94-40CF-BFFE-60D111C25037.pdf"},"width":1920,"height":1080}},"events":[{"effects":[{"beginTime":0,"baseLayer":{"animations":[],"initialState":{"affineTransform":[1,0,0,1,0,0],"masksToBounds":false,"rotation":0,"scale":1,"position":{"pointX":960,"pointY":540},"width":1920,"sublayerTransform":[1,0,0,0,0,1,0,0,0,0,1,0,0,0,0,1],"contentsRect":{"y":0,"x":0,"width":1,"height":1},"opacity":1,"edgeAntialiasingMask":251658240,"height":1080,"hidden":false,"anchorPoint":{"pointX":0.5,"pointY":0.5}},"objectID":"0","layers":[{"animations":[],"initialState":{"affineTransform":[1,0,0,1,0,0],"masksToBounds":false,"rotation":0,"scale":1,"position":{"pointX":960,"pointY":540},"width":1920,"sublayerTransform":[1,0,0,0,0,1,0,0,0,0,1,-0.00035007912466775983,0,0,0,1],"contentsRect":{"y":0,"x":0,"width":1,"height":1},"opacity":1,"edgeAntialiasingMask":251658240,"height":1080,"hidden":false,"anchorPoint":{"pointX":0.5,"pointY":0.5}},"layers":[{"animations":[],"layers":[],"texturedRectangle":{"isBackgroundTexture":false,"singleTextureOpacity":1,"textureType":0,"textBaseline":0,"textXHeight":0,"isVerticalText":false},"initialState":{"affineTransform":[1,0,0,1,0,0],"masksToBounds":false,"rotation":0,"scale":1,"position":{"pointX":960,"pointY":540},"width":1920,"sublayerTransform":[1,0,0,0,0,1,0,0,0,0,1,0,0,0,0,1],"contentsRect":{"y":0,"x":0,"width":1,"height":1},"opacity":1,"edgeAntialiasingMask":0,"height":1080,"hidden":false,"anchorPoint":{"pointX":0.5,"pointY":0.5}},"texture":"AB5BA6B3CC3DD0CDD9678F6B37984E7E"},{"animations":[{"additive":false,"timeOffset":0,"beginTime":0,"from":{"scalar":false},"repeatCount":0,"fillMode":"both","duration":0.001,"autoreverses":false,"property":"hidden","to":{"scalar":true},"removedOnCompletion":false}],"layers":[],"texturedRectangle":{"isBackgroundTexture":false,"singleTextureOpacity":1,"textureType":0,"textBaseline":0,"textXHeight":0,"isVerticalText":false},"initialState":{"affineTransform":[1,0,0,1,0,0],"masksToBounds":false,"rotation":0,"scale":1,"position":{"pointX":960,"pointY":540},"width":1920,"sublayerTransform":[1,0,0,0,0,1,0,0,0,0,1,0,0,0,0,1],"contentsRect":{"y":0,"x":0,"width":1,"height":1},"opacity":1,"edgeAntialiasingMask":0,"height":1080,"hidden":false,"anchorPoint":{"pointX":0.5,"pointY":0.5}},"texture":"77B8B06DD926AFA1AE5AE9B598D05DEF"}]}]},"effects":[],"duration":0.001,"type":"transition","attributes":{"direction":0},"name":"none","objectID":"0"}],"automaticPlay":false,"hyperlinks":[],"accessibility":[{"text":"equation.pdf","targetRectangle":{"y":570.45987601781599,"x":443.37430751800537,"width":70.417632398753881,"height":64.519756920983809}},{"text":"equation.pdf","targetRectangle":{"y":505.54011828620901,"x":599.69430751800542,"width":25.710093457943913,"height":64.519756920983809}},{"text":"Measure a set of ￼ values:","targetRectangle":{"y":338.52789306640625,"x":152.49430751800537,"width":478.39233886566944,"height":66.612224409179589}},{"text":"Find the “best fitting” normal distribution by choosing ￼ and ￼ such that the N(￼) distribution approximates the histogram of the ￼ values","targetRectangle":{"y":405.54011828620901,"x":152.49430751800537,"width":642.43999999999994,"height":349.45173987239377}},{"text":"plotname.png","targetRectangle":{"y":306.41229248046875,"x":883.21185302734375,"width":900,"height":750}},{"text":"￼","targetRectangle":{"y":325.50776147842407,"x":1396.1531982421875,"width":136.22441978193137,"height":64.519756920983866}},{"text":"Fit parameters to a set of measurements","targetRectangle":{"y":186.59999990463257,"x":98.599999904632568,"width":1011.5599999999997,"height":71.449998885393143}},{"text":"equation.pdf","targetRectangle":{"y":856.5458984375,"x":295.3577880859375,"width":340.6112887004341,"height":69.101935881203417}},{"text":"equation.pdf","targetRectangle":{"y":505.54011828620901,"x":717.04440097594932,"width":24.341495327102848,"height":64.519756920983809}},{"text":"equation.pdf","targetRectangle":{"y":688.37963374942319,"x":152.49430751800537,"width":29.632338865669368,"height":66.612224409179589}},{"text":"equation.pdf","targetRectangle":{"y":338.52789306640625,"x":464.49430751800537,"width":29.632338865669396,"height":66.612224409179589}},{"text":"equation.pdf","targetRectangle":{"y":325.50776147842407,"x":1396.1531982421875,"width":136.22441978193137,"height":64.519756920983866}},{"text":"Simplest probabilistic model","targetRectangle":{"y":54,"x":99,"width":1223.3150005733223,"height":124.04999807476997}}],"baseLayer":{"animations":[],"initialState":{"affineTransform":[1,0,0,1,0,0],"masksToBounds":false,"rotation":0,"scale":1,"position":{"pointX":960,"pointY":540},"width":1920,"sublayerTransform":[1,0,0,0,0,1,0,0,0,0,1,0,0,0,0,1],"contentsRect":{"y":0,"x":0,"width":1,"height":1},"opacity":1,"edgeAntialiasingMask":251658240,"height":1080,"hidden":false,"anchorPoint":{"pointX":0.5,"pointY":0.5}},"objectID":"0","layers":[{"animations":[],"initialState":{"affineTransform":[1,0,0,1,0,0],"masksToBounds":false,"rotation":0,"scale":1,"position":{"pointX":960,"pointY":540},"width":1920,"sublayerTransform":[1,0,0,0,0,1,0,0,0,0,1,-0.00035007912466775983,0,0,0,1],"contentsRect":{"y":0,"x":0,"width":1,"height":1},"opacity":1,"edgeAntialiasingMask":251658240,"height":1080,"hidden":false,"anchorPoint":{"pointX":0.5,"pointY":0.5}},"layers":[{"animations":[],"layers":[],"texturedRectangle":{"isBackgroundTexture":false,"singleTextureOpacity":1,"textureType":0,"textBaseline":0,"textXHeight":0,"isVerticalText":false},"initialState":{"affineTransform":[1,0,0,1,0,0],"masksToBounds":false,"rotation":0,"scale":1,"position":{"pointX":960,"pointY":540},"width":1920,"sublayerTransform":[1,0,0,0,0,1,0,0,0,0,1,0,0,0,0,1],"contentsRect":{"y":0,"x":0,"width":1,"height":1},"opacity":1,"edgeAntialiasingMask":0,"height":1080,"hidden":false,"anchorPoint":{"pointX":0.5,"pointY":0.5}},"texture":"77B8B06DD926AFA1AE5AE9B598D05DEF"}]}]}}]}